Metadata-Version: 2.4
Name: crosslab_soa_service_programming
Version: 0.4.0
Summary: The CrossLab SOA programming Service.
Author: Pierre Helbing
Author-email: pierre.helbing@tu-ilmenau.de
Classifier: Programming Language :: Python :: 3
Classifier: License :: Other/Proprietary License
Classifier: Operating System :: OS Independent
Requires-Python: <3.14,>=3.9
Requires-Dist: crosslab_soa_client
Requires-Dist: pyee
